rebrickable/__init__.py
rebrickable/api/__init__.py
rebrickable/api/api_client.py
rebrickable/api/configuration.py
rebrickable/api/exceptions.py
rebrickable/api/rest.py
rebrickable/api/api/__init__.py
rebrickable/api/api/lego_api.py
rebrickable/api/api/users_api.py
rebrickable/api/models/__init__.py
rebrickable/api/models/all_part.py
rebrickable/api/models/array_of_all_parts.py
rebrickable/api/models/array_of_badges.py
rebrickable/api/models/array_of_colors.py
rebrickable/api/models/array_of_elements.py
rebrickable/api/models/array_of_inventory_parts.py
rebrickable/api/models/array_of_lost_parts.py
rebrickable/api/models/array_of_mocs.py
rebrickable/api/models/array_of_part_categories.py
rebrickable/api/models/array_of_part_colors_elements.py
rebrickable/api/models/array_of_part_colors_lists.py
rebrickable/api/models/array_of_part_list_parts.py
rebrickable/api/models/array_of_part_lists.py
rebrickable/api/models/array_of_parts.py
rebrickable/api/models/array_of_set_list_sets.py
rebrickable/api/models/array_of_set_lists.py
rebrickable/api/models/array_of_sets.py
rebrickable/api/models/array_of_themes.py
rebrickable/api/models/badge.py
rebrickable/api/models/build.py
rebrickable/api/models/build_options.py
rebrickable/api/models/color.py
rebrickable/api/models/element.py
rebrickable/api/models/external_color_id.py
rebrickable/api/models/external_color_ids.py
rebrickable/api/models/external_ids.py
rebrickable/api/models/inventory_part.py
rebrickable/api/models/lego.py
rebrickable/api/models/lost_part.py
rebrickable/api/models/moc.py
rebrickable/api/models/part.py
rebrickable/api/models/part_category.py
rebrickable/api/models/part_colors_element.py
rebrickable/api/models/part_colors_list.py
rebrickable/api/models/part_list.py
rebrickable/api/models/part_list_part.py
rebrickable/api/models/part_list_part_item.py
rebrickable/api/models/profile.py
rebrickable/api/models/rewards.py
rebrickable/api/models/set.py
rebrickable/api/models/set_list.py
pyrebrickable-0.9.2.dist-info/METADATA
pyrebrickable-0.9.2.dist-info/WHEEL
pyrebrickable-0.9.2.dist-info/entry_points.txt
pyrebrickable-0.9.2.dist-info/top_level.txt
pyrebrickable-0.9.2.dist-info/RECORD
