Metadata-Version: 2.1
Name: pyrebrickable
Version: 0.9.2
Summary: UNKNOWN
Home-page: https://rienafairefr.github.io/pyrebrickable/
Author: rienafairefr
Author-email: rienafairefr@gmail.com
License: UNKNOWN
Keywords: rebrickable
Platform: UNKNOWN
Requires-Dist: decorator
Requires-Dist: appdirs
Requires-Dist: enum34
Requires-Dist: PyYaml
Requires-Dist: sqlalchemy
Requires-Dist: click (>=6)
Requires-Dist: urllib3 (>=1.15)
Requires-Dist: six (>=1.10)
Requires-Dist: certifi
Requires-Dist: python-dateutil
